mds/__init__.py
mds/__main__.py
mds/cli.py
mds/config.py
mds/markdown.py
mds/server.py
mds/static/favicon.ico
mds/static/markdown.css
mds/static/sam.css
mds/static/search.js
mds/static/styles.css
mds/static/utils.js
mds/views/content.tpl
mds/views/editor.tpl
mds/views/home-content.tpl
mds/views/home.tpl
mds/views/home_bar.tpl
mds/views/home_content.tpl
mds/views/homebar.tpl
mds/views/main.tpl
mds/views/main_layout.tpl
mds/views/markdown_content.tpl
mds/views/markdown_content_bar.tpl
mds/views/markdown_editor.tpl
mds/views/markdown_editor_bar.tpl
mds/views/mdbar.tpl
mds/views/mde-test.tpl
mds/views/mde.tpl
mds/views/mdebar.tpl
mds/views/nav.tpl
mds/views/searchbar.tpl
mds-0.0.6.dist-info/LICENSE
mds-0.0.6.dist-info/METADATA
mds-0.0.6.dist-info/WHEEL
mds-0.0.6.dist-info/entry_points.txt
mds-0.0.6.dist-info/top_level.txt
mds-0.0.6.dist-info/RECORD
