Metadata-Version: 2.1
Name: mds
Version: 0.0.6
Summary: Markdown Server
Home-page: https://github.com/samdixon/mds
Author: Samuel Dixon
Author-email: sdixon@posteo.net
License: MIT
Platform: UNKNOWN
Classifier: License :: OSI Approved :: MIT License
Classifier: Programming Language :: Python
Classifier: Programming Language :: Python :: 3
Classifier: Programming Language :: Python :: 3.6
Classifier: Programming Language :: Python :: Implementation :: CPython
Classifier: Programming Language :: Python :: Implementation :: PyPy
Requires-Python: >=3.6.0
Provides-Extra: dev
